<annotation>
	<folder>output</folder>
	<filename>Drone Solar Panel Inspection with FLIR-zfRaq2d0kZframe8400.jpg</filename>
	<path>/Users/TONY-STARK/SolarImaging/output/Drone Solar Panel Inspection with FLIR-zfRaq2d0kZframe8400.jpg</path>
	<source>
		<database>Unknown</database>
	</source>
	<size>
		<width>720</width>
		<height>480</height>
		<depth>3</depth>
	</size>
	<segmented>0</segmented>
	<object>
		<name>defect</name>
		<pose>Unspecified</pose>
		<truncated>0</truncated>
		<difficult>0</difficult>
		<bndbox>
			<xmin>228</xmin>
			<ymin>5</ymin>
			<xmax>242</xmax>
			<ymax>15</ymax>
		</bndbox>
	</object>
	<object>
		<name>defect</name>
		<pose>Unspecified</pose>
		<truncated>0</truncated>
		<difficult>0</difficult>
		<bndbox>
			<xmin>424</xmin>
			<ymin>159</ymin>
			<xmax>440</xmax>
			<ymax>172</ymax>
		</bndbox>
	</object>
	<object>
		<name>defect</name>
		<pose>Unspecified</pose>
		<truncated>0</truncated>
		<difficult>0</difficult>
		<bndbox>
			<xmin>502</xmin>
			<ymin>352</ymin>
			<xmax>527</xmax>
			<ymax>379</ymax>
		</bndbox>
	</object>
	<object>
		<name>defect</name>
		<pose>Unspecified</pose>
		<truncated>0</truncated>
		<difficult>0</difficult>
		<bndbox>
			<xmin>570</xmin>
			<ymin>421</ymin>
			<xmax>585</xmax>
			<ymax>436</ymax>
		</bndbox>
	</object>
	<object>
		<name>defect</name>
		<pose>Unspecified</pose>
		<truncated>0</truncated>
		<difficult>0</difficult>
		<bndbox>
			<xmin>578</xmin>
			<ymin>193</ymin>
			<xmax>602</xmax>
			<ymax>217</ymax>
		</bndbox>
	</object>
	<object>
		<name>defect</name>
		<pose>Unspecified</pose>
		<truncated>0</truncated>
		<difficult>0</difficult>
		<bndbox>
			<xmin>152</xmin>
			<ymin>194</ymin>
			<xmax>178</xmax>
			<ymax>210</ymax>
		</bndbox>
	</object>
	<object>
		<name>defect</name>
		<pose>Unspecified</pose>
		<truncated>0</truncated>
		<difficult>0</difficult>
		<bndbox>
			<xmin>398</xmin>
			<ymin>101</ymin>
			<xmax>410</xmax>
			<ymax>111</ymax>
		</bndbox>
	</object>
</annotation>
